MANIFEST.in
setup.py
django_sitemenu.egg-info/PKG-INFO
django_sitemenu.egg-info/SOURCES.txt
django_sitemenu.egg-info/dependency_links.txt
django_sitemenu.egg-info/not-zip-safe
django_sitemenu.egg-info/top_level.txt
sitemenu/__init__.py
sitemenu/admin.py
sitemenu/admin_forms.py
sitemenu/admin_views.py
sitemenu/decorators.py
sitemenu/fields.py
sitemenu/helpers.py
sitemenu/middleware.py
sitemenu/models.py
sitemenu/sitemaps.py
sitemenu/sitemenu_settings.py
sitemenu/translation.py
sitemenu/urls.py
sitemenu/views.py
sitemenu/views_mixins.py
sitemenu/locale/lv/LC_MESSAGES/django.mo
sitemenu/locale/lv/LC_MESSAGES/django.po
sitemenu/locale/ru/LC_MESSAGES/django.mo
sitemenu/locale/ru/LC_MESSAGES/django.po
sitemenu/mixins/__init__.py
sitemenu/mixins/admin_mixins.py
sitemenu/mixins/video_mixin.py
sitemenu/plugins/__init__.py
sitemenu/plugins/feedback_form/__init__.py
sitemenu/plugins/feedback_form/admin.py
sitemenu/plugins/feedback_form/forms.py
sitemenu/plugins/feedback_form/models.py
sitemenu/plugins/feedback_form/urls.py
sitemenu/plugins/feedback_form/views.py
sitemenu/plugins/feedback_form/static/sitemenu/plugins/contactform/js/contactform.js
sitemenu/plugins/feedback_form/templates/sitemenu/plugins/feedback_form/feedback_form.html
sitemenu/plugins/feedback_form/templates/sitemenu/plugins/feedback_form/feedback_form_sent.html
sitemenu/plugins/feedback_form/templates/sitemenu/plugins/feedback_form/mail_body.html
sitemenu/plugins/feedback_form/templates/sitemenu/plugins/feedback_form/mail_subject.txt
sitemenu/plugins/feedback_form/templatetags/__init__.py
sitemenu/plugins/feedback_form/templatetags/feedback_form.py
sitemenu/static/admin/sitemenu/css/images.css
sitemenu/static/admin/sitemenu/css/sitemenu.css
sitemenu/static/admin/sitemenu/css/tablefield.css
sitemenu/static/admin/sitemenu/css/no-theme/jquery-ui.min.css
sitemenu/static/admin/sitemenu/img/icon-drag.png
sitemenu/static/admin/sitemenu/js/images.js
sitemenu/static/admin/sitemenu/js/jquery-ui.min.js
sitemenu/static/admin/sitemenu/js/sitemenu.js
sitemenu/static/admin/sitemenu/js/tablefield.js
sitemenu/static/sitemenu/css/sitemenu.css
sitemenu/templates/base.html
