Metadata-Version: 1.1
Name: django-sitemenu
Version: 0.1.0
Summary: Nested menu for django projects.
Home-page: https://github.com/Brick85/sitemenu/
Author: Vital Belikov
Author-email: vital@qwe.lv
License: New BSD
Platform: UNKNOWN
Classifier: Development Status :: 5 - Production/Stable
Classifier: Environment :: Web Environment
Classifier: Framework :: Django
Classifier: Intended Audience :: Developers
Classifier: License :: OSI Approved :: BSD License
Classifier: Natural Language :: English
Classifier: Operating System :: Unix
Classifier: Programming Language :: Python :: 2.7
Classifier: Topic :: Utilities
Requires: django(>=1.3)
